Metadata-Version: 2.1
Name: probabilidad
Version: 0.1
Summary: Probabilidad usando distribucion de Gauss/ normal y distribucion binomial
Home-page: UNKNOWN
Author: Jose MARIN
Author-email: josermarinr18@gmail.com
License: UNKNOWN
Platform: UNKNOWN
Requires-Python: >=3.4^
